mcp_pokemon_server_zyq/TeaTest.py
mcp_pokemon_server_zyq/__init__.py
mcp_pokemon_server_zyq-0.1.2.dist-info/METADATA
mcp_pokemon_server_zyq-0.1.2.dist-info/WHEEL
mcp_pokemon_server_zyq-0.1.2.dist-info/entry_points.txt
mcp_pokemon_server_zyq-0.1.2.dist-info/RECORD
