Metadata-Version: 2.4
Name: mcp-pokemon-server-zyq
Version: 0.1.2
Summary: Add your description here
Author-email: 雨晴 <zhuyuqingzhuyuqing@alibaba-inc.com>
Requires-Python: >=3.10
Requires-Dist: mcp[cli]>=1.6.0
